odoo8_addon_ngo_shipment_plan-8.0.0.1.0-py2.7-nspkg.pth
odoo_addons/ngo_shipment_plan/__openerp__.py
odoo_addons/ngo_shipment_plan/__init__.py
odoo_addons/ngo_shipment_plan/README.rst
odoo_addons/ngo_shipment_plan/view/menu.xml
odoo8_addon_ngo_shipment_plan-8.0.0.1.0.dist-info/top_level.txt
odoo8_addon_ngo_shipment_plan-8.0.0.1.0.dist-info/WHEEL
odoo8_addon_ngo_shipment_plan-8.0.0.1.0.dist-info/RECORD
odoo8_addon_ngo_shipment_plan-8.0.0.1.0.dist-info/metadata.json
odoo8_addon_ngo_shipment_plan-8.0.0.1.0.dist-info/DESCRIPTION.rst
odoo8_addon_ngo_shipment_plan-8.0.0.1.0.dist-info/METADATA
odoo8_addon_ngo_shipment_plan-8.0.0.1.0.dist-info/namespace_packages.txt
